voter_case.v
module voter_case (I, O);
input [3:0] I; // I 4 men
output [3:1] O; // O Result
reg [3:1] O; 

always@ (I)
    case (I)
        4'b0000:O[3] = 1;
        4'b0001:O[3] = 1;
        4'b0010:O[3] = 1;
        4'b0011:O[2] = 1;
        4'b0100:O[3] = 1;
        4'b0101:O[2] = 1;
        4'b0110:O[2] = 1;
        4'b0111:O[1] = 1;
        4'b1000:O[3] = 1;
        4'b1001:O[2] = 1;
        4'b1010:O[2] = 1;
        4'b1011:O[1] = 1;
        4'b1100:O[2] = 1;
        4'b1101:O[1] = 1;
        4'b1110:O[1] = 1;
        4'b1111:O[1] = 1;
        default:O[1] = 0;
        default:O[2] = 0;
        default:O[3] = 0;
    endcase
endmodule

voter_case_tb.v
`timescale 1ns/1ps
module voter_case_tb ();
reg [3:0] I; // I 4 men
wire [3:1] O; // O Result

initial begin
   #5 I=4'b0000;
   #5 I=4'b0000;
   #5 I=4'b0001;
   #5 I=4'b0010;
   #5 I=4'b0011;
   #5 I=4'b0100;
   #5 I=4'b0101;
   #5 I=4'b0110;
   #5 I=4'b0111;
   #5 I=4'b1000;
   #5 I=4'b1001;
   #5 I=4'b1010;
   #5 I=4'b1011;
   #5 I=4'b1100;
   #5 I=4'b1101;
   #5 I=4'b1110;
   #5 I=4'b1111;
end

initial begin
    $dumpfile("voter_case.vcd");
    $dumpvars(0, voter_case_tb);
end

voter_case voter_case_tb(
    .I(I),
    .O(O)
);

endmodule

voter_case.vcd
$date
	Sun Apr 17 15:22:51 2022
$end
$version
	Icarus Verilog
$end
$timescale
	1ps
$end
$scope module voter_case_tb $end
$scope module voter_case_tb $end
$var wire 4 ! I [3:0] $end
$var reg 3 " O [3:1] $end
$upscope $end
$upscope $end
$enddefinitions $end
#0
$dumpvars
bx "
bx !
$end
#5000
b1xx "
b0 !
#15000
b1 !
#20000
b10 !
#25000
b11x "
b11 !
#30000
b100 !
#35000
b101 !
#40000
b110 !
#45000
b111 "
b111 !
#50000
b1000 !
#55000
b1001 !
#60000
b1010 !
#65000
b1011 !
#70000
b1100 !
#75000
b1101 !
#80000
b1110 !
#85000
b1111 !
