voter_case.v
module voter_case (I, O);
input [3:0] I; // I 4 men
output [3:1] O; // O Result
reg [3:1] O; 

always@ (I)
    case (I)
        4'b0000:O[3] = 1;
        4'b0001:O[3] = 1;
        4'b0010:O[3] = 1;
        4'b0011:O[2] = 1;
        4'b0100:O[3] = 1;
        4'b0101:O[2] = 1;
        4'b0110:O[2] = 1;
        4'b0111:O[1] = 1;
        4'b1000:O[3] = 1;
        4'b1001:O[2] = 1;
        4'b1010:O[2] = 1;
        4'b1011:O[1] = 1;
        4'b1100:O[2] = 1;
        4'b1101:O[1] = 1;
        4'b1110:O[1] = 1;
        4'b1111:O[1] = 1;
        default:O[1] = 0;
        default:O[2] = 0;
        default:O[3] = 0;
    endcase
endmodule

voter_case_tb.v
`timescale 1ns/1ps
module voter_case_tb ();
reg [3:0] I; // I 4 men
wire [3:1] O; // O Result

initial begin
   #100 I=4'b0000;
   #100 I=4'b0000;
   #100 I=4'b0001;
   #100 I=4'b0010;
   #100 I=4'b0011;
   #100 I=4'b0100;
   #100 I=4'b0101;
   #100 I=4'b0110;
   #100 I=4'b0111;
   #100 I=4'b1000;
   #100 I=4'b1001;
   #100 I=4'b1010;
   #100 I=4'b1011;
   #100 I=4'b1100;
   #100 I=4'b1101;
   #100 I=4'b1110;
   #100 I=4'b1111;
end

initial begin
    $dumpfile("voter_case.vcd");
    $dumpvars(0, voter_case_tb);
end

voter_case voter_case_tb(
    .I(I),
    .O(O)
);

endmodule

voter_case.vcd
$date
	Sun Apr 17 15:28:38 2022
$end
$version
	Icarus Verilog
$end
$timescale
	1ps
$end
$scope module voter_case_tb $end
$scope module voter_case_tb $end
$var wire 4 ! I [3:0] $end
$var reg 3 " O [3:1] $end
$upscope $end
$upscope $end
$enddefinitions $end
#0
$dumpvars
bx "
bx !
$end
#100000
b1xx "
b0 !
#300000
b1 !
#400000
b10 !
#500000
b11x "
b11 !
#600000
b100 !
#700000
b101 !
#800000
b110 !
#900000
b111 "
b111 !
#1000000
b1000 !
#1100000
b1001 !
#1200000
b1010 !
#1300000
b1011 !
#1400000
b1100 !
#1500000
b1101 !
#1600000
b1110 !
#1700000
b1111 !
